main.py
strategy_backtesting-0.1.0.dist-info/METADATA
strategy_backtesting-0.1.0.dist-info/WHEEL
strategy_backtesting-0.1.0.dist-info/top_level.txt
strategy_backtesting-0.1.0.dist-info/RECORD
