Metadata-Version: 2.4
Name: strategy_backtesting
Version: 0.1.0
Summary: Test your own strategies with python and a dataset. A hackclub siege project
Requires-Python: >=3.13
Requires-Dist: matplotlib>=3.10.7
Requires-Dist: pandas>=2.3.3
